[{"id":"rv86qiiAL9ff4fMhkprgV","userId":1,"category":"gff","urgency":"dfg","message":"sfg","imagePath":"https://res.cloudinary.com/drrib5e16/image/upload/v1773071867/ytffbwjnkvl09jem6vrk.webp","sourceType":"form","createdAt":"2026-03-09T15:57:47.426Z"},{"id":"YFIO0aAVi32BLvmSmIgEb","userId":1,"category":"gff","urgency":"dfg","message":"sfg","imagePath":"https://res.cloudinary.com/drrib5e16/image/upload/v1773132363/ugqrame74cvwrkzmx3kl.webp","sourceType":"form","createdAt":"2026-03-10T08:46:02.908Z"},{"id":"Wmb3nmQJkk2wETZ5EsAhJ","userId":1,"category":"Security","urgency":"High","message":"Main gate sensor is not responding","imagePath":null,"sourceType":"csv file","createdAt":"Tue Mar 10 2026"},{"id":"6QN9pJFfigFkhevtTKUPG","userId":1,"category":"Maintenance","urgency":"Low","message":"Leaking faucet in the second floor restroom","imagePath":null,"sourceType":"csv file","createdAt":"Tue Mar 10 2026"},{"id":"iwhNzfFqLc-0fd3KSmjom","userId":1,"category":"Safety","urgency":"Medium","message":"Emergency exit sign is flickering","imagePath":null,"sourceType":"csv file","createdAt":"Tue Mar 10 2026"}]